uipath_orchestrator_rest/__init__.py
uipath_orchestrator_rest/api_client.py
uipath_orchestrator_rest/configuration.py
uipath_orchestrator_rest/rest.py
uipath_orchestrator_rest/api/__init__.py
uipath_orchestrator_rest/api/account_api.py
uipath_orchestrator_rest/api/alerts_api.py
uipath_orchestrator_rest/api/app_tasks_api.py
uipath_orchestrator_rest/api/assets_api.py
uipath_orchestrator_rest/api/audit_logs_api.py
uipath_orchestrator_rest/api/buckets_api.py
uipath_orchestrator_rest/api/calendars_api.py
uipath_orchestrator_rest/api/credential_stores_api.py
uipath_orchestrator_rest/api/directory_service_api.py
uipath_orchestrator_rest/api/environments_api.py
uipath_orchestrator_rest/api/execution_media_api.py
uipath_orchestrator_rest/api/exports_api.py
uipath_orchestrator_rest/api/folders_api.py
uipath_orchestrator_rest/api/folders_navigation_api.py
uipath_orchestrator_rest/api/generic_tasks_api.py
uipath_orchestrator_rest/api/host_licenses_api.py
uipath_orchestrator_rest/api/job_triggers_api.py
uipath_orchestrator_rest/api/jobs_api.py
uipath_orchestrator_rest/api/libraries_api.py
uipath_orchestrator_rest/api/licenses_named_user_api.py
uipath_orchestrator_rest/api/licenses_runtime_api.py
uipath_orchestrator_rest/api/licensing_api.py
uipath_orchestrator_rest/api/logs_api.py
uipath_orchestrator_rest/api/machines_api.py
uipath_orchestrator_rest/api/maintenance_api.py
uipath_orchestrator_rest/api/organization_units_api.py
uipath_orchestrator_rest/api/package_feeds_api.py
uipath_orchestrator_rest/api/permissions_api.py
uipath_orchestrator_rest/api/personal_workspaces_api.py
uipath_orchestrator_rest/api/process_schedules_api.py
uipath_orchestrator_rest/api/processes_api.py
uipath_orchestrator_rest/api/queue_definitions_api.py
uipath_orchestrator_rest/api/queue_item_comments_api.py
uipath_orchestrator_rest/api/queue_item_events_api.py
uipath_orchestrator_rest/api/queue_items_api.py
uipath_orchestrator_rest/api/queue_processing_records_api.py
uipath_orchestrator_rest-18.1.dist-info/LICENSE.md
uipath_orchestrator_rest-18.1.dist-info/METADATA
uipath_orchestrator_rest-18.1.dist-info/WHEEL
uipath_orchestrator_rest-18.1.dist-info/top_level.txt
uipath_orchestrator_rest-18.1.dist-info/RECORD
